__init__.py
aggregate.py
choicellm.py
multichoicemodel.py
prompttemplate.py
choicellm-0.2.1.dist-info/licenses/LICENSE
choicellm-0.2.1.dist-info/METADATA
choicellm-0.2.1.dist-info/WHEEL
choicellm-0.2.1.dist-info/entry_points.txt
choicellm-0.2.1.dist-info/top_level.txt
choicellm-0.2.1.dist-info/RECORD
