Metadata-Version: 2.4
Name: choicellm
Version: 0.2.1
Summary: Using LLMs for rating items on a scale, comparative judgments, and multiple choice questions.
Author-email: Matthijs Westera <m.westera@hum.leidenuniv.nl>
Project-URL: Homepage, https://github.com/mwestera/choicellm
Project-URL: Bug Tracker, https://github.com/mwestera/choicellm/issues
Classifier: Programming Language :: Python :: 3
Classifier: Operating System :: OS Independent
Classifier: Development Status :: 3 - Alpha
Classifier: Intended Audience :: Science/Research
Classifier: Topic :: Scientific/Engineering :: Artificial Intelligence
Classifier: Topic :: Text Processing :: Linguistic
Requires-Python: >=3.10
License-File: LICENSE
Requires-Dist: transformers
Requires-Dist: torch
Requires-Dist: accelerate
Requires-Dist: optimum
Requires-Dist: bitsandbytes
Requires-Dist: openai
Requires-Dist: tiktoken
Requires-Dist: pandas
Dynamic: license-file
